topsis/__init__.py
topsis/__main__.py
Topsis_Prateek_101916078-1.0.4.dist-info/LICENSE
Topsis_Prateek_101916078-1.0.4.dist-info/METADATA
Topsis_Prateek_101916078-1.0.4.dist-info/WHEEL
Topsis_Prateek_101916078-1.0.4.dist-info/entry_points.txt
Topsis_Prateek_101916078-1.0.4.dist-info/top_level.txt
Topsis_Prateek_101916078-1.0.4.dist-info/RECORD
