Metadata-Version: 2.1
Name: Topsis-Prateek-101916078
Version: 1.0.4
Summary: Topsis in python that take input csv file and outputs csv file
Home-page: https://github.com/prateek11rai/Topsis-Prateek-101916078
Author: Prateek Rai
Author-email: prateek11rai@gmail.com
License: MIT
Platform: UNKNOWN
Classifier: License :: OSI Approved :: MIT License
Classifier: Programming Language :: Python :: 3.6
Classifier: Programming Language :: Python :: 3.7
Classifier: Programming Language :: Python :: 3.8
License-File: LICENSE
Requires-Dist: pandas
